modern_di_litestar/__init__.py
modern_di_litestar/main.py
modern_di_litestar/py.typed
modern_di_litestar-2.2.0.dist-info/METADATA
modern_di_litestar-2.2.0.dist-info/WHEEL
modern_di_litestar-2.2.0.dist-info/RECORD
