Metadata-Version: 2.4
Name: modern-di-litestar
Version: 2.2.0
Summary: Modern-DI integration for LiteStar
Project-URL: repository, https://github.com/modern-python/modern-di
Project-URL: docs, https://modern-di.readthedocs.io
Author-email: Artur Shiriev <me@shiriev.ru>
License-Expression: MIT
Keywords: DI,LiteStar,dependency injector,ioc-container,python
Classifier: Programming Language :: Python :: 3.10
Classifier: Programming Language :: Python :: 3.11
Classifier: Programming Language :: Python :: 3.12
Classifier: Programming Language :: Python :: 3.13
Classifier: Programming Language :: Python :: 3.14
Classifier: Topic :: Software Development :: Libraries
Classifier: Typing :: Typed
Requires-Python: <4,>=3.10
Requires-Dist: litestar
Requires-Dist: modern-di>=2
